quick_titan/__init__.py
quick_titan/analyzer.py
quick_titan/cli.py
quick_titan-0.1.0.dist-info/METADATA
quick_titan-0.1.0.dist-info/WHEEL
quick_titan-0.1.0.dist-info/entry_points.txt
quick_titan-0.1.0.dist-info/top_level.txt
quick_titan-0.1.0.dist-info/RECORD
