Metadata-Version: 2.1
Name: quick-titan
Version: 0.1.0
Summary: A package to analyze customer data from a CSV file.
Author: Semyon Drozdov
Author-email: Semyon Drozdov <s.drozdov@edu.centraluniversity.ru>
